{"stat.walkOneCm":13674,"stat.leaveGame":1,"stat.mineBlock.minecraft.cobblestone":1,"stat.damageTaken":930,"stat.useItem.minecraft.cobblestone":1,"stat.useItem.minecraft.diamond_pickaxe":6,"stat.mobKills":7,"stat.pickup.minecraft.cobblestone":1,"stat.useItem.minecraft.diamond_sword":14,"stat.talkedToVillager":8,"stat.flyOneCm":100700,"stat.deaths":2,"stat.pickup.minecraft.wheat_seeds":1,"stat.jump":124,"stat.swimOneCm":1412,"stat.playOneMinute":11627,"stat.fallOneCm":32949,"stat.pickup.minecraft.rabbit_hide":2,"stat.killEntity.Sheep":6,"stat.sneakTime":42,"stat.pickup.minecraft.wool":7,"stat.pickup.minecraft.rabbit":3,"stat.damageDealt":500,"stat.killEntity.Rabbit":1,"stat.useItem.minecraft.wool":1,"stat.mineBlock.minecraft.wool":1,"stat.timeSinceDeath":6029,"stat.pickup.minecraft.sapling":1,"stat.pickup.minecraft.dirt":9,"stat.sprintOneCm":22351,"stat.mineBlock.minecraft.dirt":3,"stat.mineBlock.minecraft.tallgrass":9,"stat.pickup.minecraft.mutton":4,"stat.diveOneCm":4425,"stat.pickup.minecraft.cooked_mutton":11}